rouse.py
rouse-0.1.2.dist-info/METADATA
rouse-0.1.2.dist-info/WHEEL
rouse-0.1.2.dist-info/licenses/LICENSE
rouse-0.1.2.dist-info/RECORD
