Metadata-Version: 2.4
Name: rouse
Version: 0.1.2
Summary: An implementation of the Rouse model of polymer dynamics
Project-URL: Homepage, https://github.com/OpenTrajectoryAnalysis/rouse
Project-URL: Documentation, https://rouse.readthedocs.org/en/latest
Project-URL: Bug Tracker, https://github.com/OpenTrajectoryAnalysis/rouse/issues
Author-email: Simon Grosse-Holz <sgh256@mit.edu>
License: MIT License
License-File: LICENSE
Classifier: License :: OSI Approved :: MIT License
Classifier: Operating System :: OS Independent
Classifier: Programming Language :: Python :: 3
Requires-Python: >=3.7
Requires-Dist: numpy>=1.20
Requires-Dist: scipy>=1.6
